[{"id":"tuc_0001","nome":"Abacate","origem":"tucunduva","grupo":"frutas","P":1.99,"C":7.4,"G":15.3,"kcal":161},{"id":"tuc_0002","nome":"Abacaxi","origem":"tucunduva","grupo":"frutas","P":0.39,"C":12.4,"G":0.43,"kcal":49},{"id":"tuc_0003","nome":"Arroz branco (cozido)","origem":"tucunduva","grupo":"carboidratos","P":2.32,"C":25.47,"G":1.18,"kcal":125},{"id":"taco_0001","nome":"Frango grelhado (peito)","origem":"taco","grupo":"proteinas","P":31.0,"C":0.0,"G":3.6,"kcal":165},{"id":"taco_0002","nome":"Tilápia crua","origem":"taco","grupo":"proteinas","P":20.0,"C":0.0,"G":1.7,"kcal":96},{"id":"taco_0003","nome":"Arroz branco cozido","origem":"taco","grupo":"carboidratos","P":2.5,"C":28.0,"G":0.3,"kcal":130}]